{
  "hash": "4fce74f9",
  "configHash": "64f57b0b",
  "lockfileHash": "167f9146",
  "browserHash": "c675bb15",
  "optimized": {
    "react/jsx-dev-runtime": {
      "src": "../../node_modules/react/jsx-dev-runtime.js",
      "file": "react_jsx-dev-runtime.js",
      "fileHash": "ae541932",
      "needsInterop": true
    },
    "react": {
      "src": "../../node_modules/react/index.js",
      "file": "react.js",
      "fileHash": "ad67e396",
      "needsInterop": true
    },
    "react-dom/client": {
      "src": "../../node_modules/react-dom/client.js",
      "file": "react-dom_client.js",
      "fileHash": "5f2a6df1",
      "needsInterop": true
    },
    "firebase/auth": {
      "src": "../../node_modules/firebase/auth/dist/esm/index.esm.js",
      "file": "firebase_auth.js",
      "fileHash": "5d0afb72",
      "needsInterop": false
    },
    "firebase/app": {
      "src": "../../node_modules/firebase/app/dist/esm/index.esm.js",
      "file": "firebase_app.js",
      "fileHash": "7a2278c1",
      "needsInterop": false
    },
    "firebase/firestore": {
      "src": "../../node_modules/firebase/firestore/dist/esm/index.esm.js",
      "file": "firebase_firestore.js",
      "fileHash": "a4139729",
      "needsInterop": false
    }
  },
  "chunks": {
    "chunk-I7K6YDV4": {
      "file": "chunk-I7K6YDV4.js"
    },
    "chunk-L3ZYWHL6": {
      "file": "chunk-L3ZYWHL6.js"
    },
    "chunk-BUSYA2B4": {
      "file": "chunk-BUSYA2B4.js"
    }
  }
}